PyFireStore-0.2.dist-info/METADATA
PyFireStore-0.2.dist-info/RECORD
PyFireStore-0.2.dist-info/WHEEL
PyFireStore-0.2.dist-info/top_level.txt
pyfirestore/__init__.py
pyfirestore/pyfirestore.py
