Metadata-Version: 2.1
Name: PyFireStore
Version: 0.2
Summary: Python wrapper around Google's FireStore API.
Home-page: https://bitbucket.org/gingalabdev/pyfirestore
Author: Brice Parent - GingaLab
Author-email: bparent@gingalab.com
License: Apache
Keywords: Python FireStore
Platform: UNKNOWN
Requires-Dist: google-cloud-firestore (<0.29,>=0.28.0)
